quizdom/__init__.py
quizdom-0.3.0.dist-info/METADATA
quizdom-0.3.0.dist-info/WHEEL
quizdom-0.3.0.dist-info/RECORD
